active_learn/__init__.py
active_learn/active_model.py
active_learn/active_sampler.py
active_learn-0.0.0.dist-info/METADATA
active_learn-0.0.0.dist-info/WHEEL
active_learn-0.0.0.dist-info/licenses/LICENSE
active_learn-0.0.0.dist-info/RECORD
