Metadata-Version: 2.1
Name: active_learn
Version: 0.0.0
Summary: A tool for Deep Active Learning
Project-URL: Homepage, https://github.com/microsoft/ActiveLearn
Project-URL: Bug Tracker, https://github.com/microsoft/ActiveLearn/issues
Author-email: Wangda Zhang <wangdazhang@microsoft.com>, Jordan Ash <ash.jordan@microsoft.com>
License-File: LICENSE
Classifier: License :: OSI Approved :: MIT License
Classifier: Operating System :: OS Independent
Classifier: Programming Language :: Python :: 3
Requires-Python: >=3.8
Requires-Dist: numpy
Requires-Dist: torch
